{
  "schema_version": "2.0.0",
  "program_id": "JARVIS-100-PERCENT-COMPLETION-V2",
  "snapshot_date": "2026-07-21",
  "state": "ACTIVE_PROGRAM_NOT_100_PERCENT",
  "execution_method": "BREADTH_FIRST_MICRO_PASSES",
  "completion_formula": "minimum(mandatory source, requirement, artifact, test_or_waiver, evidence, staging, production, acceptance gate percentages)",
  "pass_rules": {
    "target_micro_slices": "3-7",
    "branch_required": true,
    "tests_required": true,
    "evidence_required": true,
    "rollback_required": true,
    "green_only_merge": true,
    "non_blocking_work_continues_around_external_gates": true,
    "no_false_100_percent": true
  },
  "blocks": [
    {"block":"A","name":"Truth denominator and persistent Knowledge Fabric","tracker_tasks":["P1-2","P2-1","P2-2","P2-4"],"exit_gate":"Persistent source graph, counted denominator and passing no-gaps verifier"},
    {"block":"B","name":"Sovereign control plane, security and operations","tracker_tasks":["P1-6","P2-2","P2-6"],"exit_gate":"Enforced policies plus proven backup, restore and rollback"},
    {"block":"C","name":"Model router, intelligence fabric and capability sourcing","tracker_tasks":["P2-5","P2-6"],"exit_gate":"Deterministic routing, evidence-ranked retrieval and quarantine decisions"},
    {"block":"D","name":"Command Centre and operator UX","tracker_tasks":["P1-5"],"exit_gate":"Truthful local or staging dashboard with tested failure states"},
    {"block":"E","name":"Automation, integration and persistence","tracker_tasks":["P0-4","P0-7","P1-1","P1-3","P1-4","P4-1"],"exit_gate":"Signed staging canaries with retry, replay protection and rollback evidence"},
    {"block":"F","name":"CFO, trading research, revenue and product domains","tracker_tasks":["P3-1","P3-2","P3-3","P3-4","P3-5","P3-6"],"exit_gate":"One verified bounded staging slice for each applicable factory"},
    {"block":"G","name":"External P0 recovery and provider gates","tracker_tasks":["P0-1","P0-2","P0-3","P0-4","P0-5","P0-6","P0-7"],"exit_gate":"Each task DONE_VERIFIED or remains BLOCKED with exact owner action"},
    {"block":"H","name":"Full staging federation","tracker_tasks":["P4-1"],"exit_gate":"Critical paths pass end-to-end and disaster-recovery tests"},
    {"block":"I","name":"Controlled production promotion","tracker_tasks":["P5-1"],"exit_gate":"Production services DONE_VERIFIED after approval"},
    {"block":"J","name":"Final reconciliation and owner acceptance","tracker_tasks":["P6-1"],"exit_gate":"All in-scope items DONE_VERIFIED or owner-accepted WAIVED"}
  ],
  "passes": [
    {"pass_id":1,"name":"Persistent source truth","state":"NEXT","micro_slices":["Knowledge Fabric SQLite migrations","Idempotent repository API","ChatHub CLI ingestion","Per-message manifest","Synthesis coverage and no-gaps verifier","Tests and CI"]},
    {"pass_id":2,"name":"Governance foundation","state":"QUEUED","micro_slices":["Build Contract schema","Dependency graph","Approval and evidence envelopes","Policy and safe-stop tests","Secret-reference readiness"]},
    {"pass_id":3,"name":"Intelligence and routing","state":"QUEUED","micro_slices":["Model registry","Free-first router","Source trust and freshness scoring","Capability quarantine batch"]},
    {"pass_id":4,"name":"Operator visibility","state":"QUEUED","micro_slices":["Truthful status API","Progress cards","Approval packets","Evidence and rollback display"]},
    {"pass_id":5,"name":"Integration standard","state":"QUEUED","micro_slices":["Signed envelope","Adapter contract","Idempotency","Retry and dead-letter","Local federation tests"]},
    {"pass_id":6,"name":"Historical bounded batches","state":"QUEUED","micro_slices":["Next accessible archive batch","Health claim tranche","Next XRP HBAR tranche when sources exist"]},
    {"pass_id":7,"name":"Domain scaffolds","state":"QUEUED","micro_slices":["AI CFO read-only slice","Paper-trading slice","Digital agency offer slice","SaaS product slice"]},
    {"pass_id":8,"name":"Connected staging proofs","state":"BLOCKED_PARTIAL","micro_slices":["Connect approved services","VTI Hub canary","Property canary","Health canary","Source-intake canary"]},
    {"pass_id":9,"name":"Full staging federation","state":"DEPENDENCY_BLOCKED","micro_slices":["End-to-end scenarios","Negative tests","Disaster exercises"]},
    {"pass_id":10,"name":"Production readiness","state":"OWNER_PROVIDER_BLOCKED","micro_slices":["Resolve P0 gates","Readiness packets","Approval packets"]},
    {"pass_id":11,"name":"Controlled production promotion","state":"OWNER_APPROVAL_BLOCKED","micro_slices":["Canary promotion","One-module-at-a-time expansion","Runtime proof"]},
    {"pass_id":12,"name":"Final reconciliation","state":"DEPENDENCY_BLOCKED","micro_slices":["No-gaps audit","Independent review","Continuity pack","Owner acceptance"]}
  ],
  "next_action": "Execute Pass 1 on a new implementation branch; test, open PR, repair to green and merge only with evidence.",
  "truth_boundary": "This registry is an execution plan, not proof of implementation, staging, deployment or production completion."
}
